LICENSE
MANIFEST.in
README.md
relevancer.py
requirements.txt
setup.py
relevancer.egg-info/PKG-INFO
relevancer.egg-info/SOURCES.txt
relevancer.egg-info/dependency_links.txt
relevancer.egg-info/requires.txt
relevancer.egg-info/top_level.txt