Metadata-Version: 1.1
Name: relevancer
Version: 0.1.0a1
Summary: Relevancer aims at identifying relevant content in social media streams. Text mining is the main approach.
Home-page: https://bitbucket.org/hurrial/relevancerml
Author: Ali Hürriyetoğlu
Author-email: ali.hurriyetoglu@gmail.com
License: GPL
Keywords: machine-learning text-mining clustering k-means
Platform: UNKNOWN
Classifier: Development Status :: 3 - Alpha
Classifier: Intended Audience :: Developers
Classifier: Intended Audience :: Science/Research
Classifier: Topic :: Text Processing :: Linguistic
Classifier: License :: OSI Approved :: GNU General Public License v3 (GPLv3)
Classifier: Programming Language :: Python :: 3.3
Classifier: Programming Language :: Python :: 3.4
Classifier: Programming Language :: Python :: 3.5
Classifier: Programming Language :: Python :: 3.6
